imap_storage/__init__.py
imap_storage/account.py
imap_storage/connection/__init__.py
imap_storage/connection/config.py
imap_storage/connection/imap.py
imap_storage/storage/__init__.py
imap_storage/storage/directory.py
imap_storage/storage/storage.py
imap_storage/storage/email/__init__.py
imap_storage/storage/email/address.py
imap_storage/storage/email/body.py
imap_storage/storage/email/email.py
imap_storage/storage/email/file.py
imap_storage/storage/email/head.py
imap_storage/tools/__init__.py
imap_storage/tools/compare.py
imap_storage/tools/timer.py
tests/__init__.py
tests/secrets.py
tests/secrets.sample.py
tests/test_account.py
tests/test_connection.py
tests/test_directory.py
tests/test_email.py
tests/test_example.py
tests/test_storage.py
imap_storage-0.2.1.dist-info/LICENSE.txt
imap_storage-0.2.1.dist-info/METADATA
imap_storage-0.2.1.dist-info/WHEEL
imap_storage-0.2.1.dist-info/top_level.txt
imap_storage-0.2.1.dist-info/RECORD
