Metadata-Version: 2.1
Name: imap-storage
Version: 0.2.1
Summary: Use your Email-account as Storage for data structures and files
Home-page: https://github.com/snake-soft/imap-storage
Author: Snake-Soft
Author-email: info@snake-soft.com
License: UNKNOWN
Project-URL: Bug Reports, https://github.com/snake-soft/imap-storage/issues/
Project-URL: Source, https://github.com/snake-soft/imap-storage/
Keywords: imap email storage data files
Platform: UNKNOWN
Classifier: Development Status :: 3 - Alpha
Classifier: Intended Audience :: Developers
Classifier: Topic :: System :: Filesystems
Classifier: License :: OSI Approved :: GNU General Public License v3 (GPLv3)
Classifier: Programming Language :: Python :: 3
Classifier: Programming Language :: Python :: 3.5
Classifier: Programming Language :: Python :: 3.6
Classifier: Programming Language :: Python :: 3.7
Requires-Python: !=2.*, !=3.0.*, !=3.1.*, !=3.2.*, !=3.3.*, !=3.4.*, <4
Requires-Dist: imapclient
Requires-Dist: lxml
Provides-Extra: dev
Requires-Dist: check-manifest ; extra == 'dev'
Provides-Extra: test
Requires-Dist: coverage ; extra == 'test'
Requires-Dist: pylint ; extra == 'test'
